[
{
    "model": "clients.client",
    "pk": 1,
    "fields": {
        "email": "test1@mail.com",
        "first_name": "petr",
        "last_name": "petrov",
        "comment": "comment #1",
        "is_active": false,
        "owner": 1
    }
},
{
    "model": "clients.client",
    "pk": 2,
    "fields": {
        "email": "test2@mail.com",
        "first_name": "ivan",
        "last_name": "ivanov",
        "comment": "comment #2",
        "is_active": false,
        "owner": 10
    }
},
{
    "model": "clients.client",
    "pk": 3,
    "fields": {
        "email": "test3@mail.com",
        "first_name": "semen",
        "last_name": "semenov",
        "comment": "comment #3",
        "is_active": false,
        "owner": 1
    }
},
{
    "model": "clients.client",
    "pk": 4,
    "fields": {
        "email": "test4@mail.com",
        "first_name": "dmitry",
        "last_name": "dmitrievich",
        "comment": "comment #4",
        "is_active": false,
        "owner": 1
    }
},
{
    "model": "clients.client",
    "pk": 5,
    "fields": {
        "email": "test6@mail.com",
        "first_name": "Aleksandr",
        "last_name": "Aleksandroff",
        "comment": "send 6",
        "is_active": true,
        "owner": 10
    }
},
{
    "model": "clients.client",
    "pk": 6,
    "fields": {
        "email": "test7@mail.com",
        "first_name": "Татьяна",
        "last_name": "Самохина",
        "comment": "клиент с активной записью об авторе",
        "is_active": true,
        "owner": 1
    }
},
{
    "model": "clients.client",
    "pk": 7,
    "fields": {
        "email": "saikaoduvan@gmail.com",
        "first_name": "saika",
        "last_name": "s",
        "comment": "test",
        "is_active": true,
        "owner": 1
    }
}
]
